fsource/__init__.py
fsource/__main__.py
fsource/analyzer.py
fsource/common.py
fsource/lexer.py
fsource/parser.py
fsource/splicer.py
fsource-0.4.1.dist-info/LICENSE.txt
fsource-0.4.1.dist-info/METADATA
fsource-0.4.1.dist-info/WHEEL
fsource-0.4.1.dist-info/entry_points.txt
fsource-0.4.1.dist-info/top_level.txt
fsource-0.4.1.dist-info/zip-safe
fsource-0.4.1.dist-info/RECORD
