Metadata-Version: 2.1
Name: fsource
Version: 0.4.1
Summary: Static analysis tools for Fortran, written in pure Python
Home-page: https://github.com/mwallerb/fsource
Author: Markus Wallerberger
Author-email: markus.wallerberger@tuwien.ac.at
License: UNKNOWN
Keywords: fortran lexer parser analysis
Platform: UNKNOWN
Classifier: Development Status :: 3 - Alpha
Classifier: Intended Audience :: Developers
Classifier: Topic :: Software Development :: Build Tools
Classifier: License :: OSI Approved :: GNU Lesser General Public License v3 (LGPLv3)
Classifier: Programming Language :: Python :: 2
Classifier: Programming Language :: Python :: 2.7
Classifier: Programming Language :: Python :: 3
Requires-Python: >=2.7, <4
Provides-Extra: dev
Requires-Dist: pylint ; extra == 'dev'
Requires-Dist: pytest ; extra == 'dev'
